azcopy_wrapper/__init__.py
azcopy_wrapper/azcopy_client.py
azcopy_wrapper/azcopy_summary.py
azcopy_wrapper/azcopy_utilities.py
azcopy_wrapper/sas_token_validation.py
azcopy_wrapper/utils/__init__.py
azcopy_wrapper/utils/constants.py
azcopy_wrapper/utils/execute_command.py
azcopy_wrapper-1.0.0.dist-info/LICENSE.md
azcopy_wrapper-1.0.0.dist-info/METADATA
azcopy_wrapper-1.0.0.dist-info/WHEEL
azcopy_wrapper-1.0.0.dist-info/top_level.txt
azcopy_wrapper-1.0.0.dist-info/RECORD
