Metadata-Version: 2.1
Name: azcopy-wrapper
Version: 1.0.0
Summary: A simple AzCopy wrapper to transfer data
Home-page: https://github.com/yashmarathe21/py-azcopy-wrapper
Author: Kurien Zacharia, Yash Marathe
Author-email: yashmarathe21@gmail.com
License: MIT
Keywords: azcopy wrapper python azure storage bulk upload blob sync copy
Classifier: License :: OSI Approved :: MIT License
Classifier: Programming Language :: Python :: 3
Classifier: Operating System :: OS Independent
Requires-Python: >=3.6
License-File: LICENSE.md
